sqp/__init__.py
sqp/auth.py
sqp/db.py
sqp/dialects/__init__.py
sqp/dialects/sql.py
sqp/dialects/sqlite.py
sqp/drivers/__init__.py
sqp/drivers/sqlite.py
sqp/objects.py
sqp/query.py
sqp/tools/__init__.py
sqp/tools/cacher.c
sqp/tools/cacher.cpython-310-x86_64-linux-gnu.so
sqp/tools/cacher.html
sqp/tools/cacher.pyx
sqp-0.2.dist-info/LICENSE
sqp-0.2.dist-info/METADATA
sqp-0.2.dist-info/WHEEL
sqp-0.2.dist-info/RECORD
