Metadata-Version: 2.1
Name: sqp
Version: 0.2
Summary: 
Author: Sven Keimpema
Requires-Python: >=3.10,<4.0
Classifier: Programming Language :: Python :: 3
Classifier: Programming Language :: Python :: 3.10
Classifier: Programming Language :: Python :: 3.11
Requires-Dist: numba (>=1.24.4,<2.0.0)
